dflow_phonon-0.0.26.data/scripts/dflowphonon
dflowphonon/ABACUS_OPs.py
dflowphonon/ABACUS_flow.py
dflowphonon/DP_OPs.py
dflowphonon/DP_flow.py
dflowphonon/VASP_OPs.py
dflowphonon/VASP_flow.py
dflowphonon/__init__.py
dflowphonon/lib/__init__.py
dflowphonon/lib/kpath.py
dflowphonon/lib/plot.py
test/__init__.py
test/context.py
test/op/__init__.py
test/op/context.py
test/op/test_make.py
dflow_phonon-0.0.26.dist-info/LICENSE
dflow_phonon-0.0.26.dist-info/METADATA
dflow_phonon-0.0.26.dist-info/WHEEL
dflow_phonon-0.0.26.dist-info/top_level.txt
dflow_phonon-0.0.26.dist-info/RECORD
